npx/__init__.py
npx/__init__.pyi
npx/_isin.py
npx/_isin.pyi
npx/_main.py
npx/_main.pyi
npx/_mean.py
npx/_mean.pyi
npx/_unique.py
npx/_unique.pyi
npx/py.typed
npx-0.1.4.dist-info/LICENSE
npx-0.1.4.dist-info/METADATA
npx-0.1.4.dist-info/WHEEL
npx-0.1.4.dist-info/top_level.txt
npx-0.1.4.dist-info/RECORD
