Metadata-Version: 2.1
Name: npx
Version: 0.1.4
Summary: Some useful extensions for NumPy
Author-email: Nico Schlömer <nico.schloemer@gmail.com>
License: Copyright 2021-present Nico Schlömer
Project-URL: Code, https://github.com/sigma-py/npx
Project-URL: Issues, https://github.com/sigma-py/npx/issues
Classifier: Development Status :: 4 - Beta
Classifier: Intended Audience :: Science/Research
Classifier: License :: OSI Approved :: BSD License
Classifier: Operating System :: OS Independent
Classifier: Programming Language :: Python
Classifier: Programming Language :: Python :: 3
Classifier: Programming Language :: Python :: 3.7
Classifier: Programming Language :: Python :: 3.8
Classifier: Programming Language :: Python :: 3.9
Classifier: Programming Language :: Python :: 3.10
Classifier: Programming Language :: Python :: 3.11
Classifier: Programming Language :: Python :: 3.12
Classifier: Topic :: Scientific/Engineering
Classifier: Topic :: Utilities
Requires-Python: >=3.7
License-File: LICENSE
Requires-Dist: numpy >=1.20.0
